LICENSE
README.md
setup.cfg
setup.py
mdiff/__init__.py
mdiff/block_extractor.py
mdiff/cli.py
mdiff/differ.py
mdiff/text_diff.py
mdiff/utils.py
mdiff.egg-info/PKG-INFO
mdiff.egg-info/SOURCES.txt
mdiff.egg-info/dependency_links.txt
mdiff.egg-info/entry_points.txt
mdiff.egg-info/requires.txt
mdiff.egg-info/top_level.txt
mdiff/seqmatch/__init__.py
mdiff/seqmatch/heckel.py
mdiff/seqmatch/utils.py
mdiff/visualisation/__init__.py
mdiff/visualisation/terminal.py
mdiff/visualisation/gui_tkinter/__init__.py
mdiff/visualisation/gui_tkinter/diff_input.py
mdiff/visualisation/gui_tkinter/diff_result.py
mdiff/visualisation/gui_tkinter/main.py
mdiff/visualisation/gui_tkinter/utils.py