Metadata-Version: 2.1
Name: mdiff
Version: 0.1.5
Summary: Sequence matcher with displacement detection.
Home-page: https://github.com/m-matelski/mdiff
Author: Mateusz Matelski
Author-email: m.z.matelski@gmail.com
License: MIT
Keywords: sequence,diff,heckel,text
Platform: UNKNOWN
Classifier: Development Status :: 3 - Alpha
Classifier: Intended Audience :: Developers
Classifier: Topic :: Software Development :: Libraries :: Python Modules
Classifier: License :: OSI Approved :: MIT License
Classifier: Programming Language :: Python :: 3.8
Classifier: Programming Language :: Python :: 3.9
Classifier: Programming Language :: Python :: 3.10
Classifier: Operating System :: MacOS :: MacOS X
Classifier: Operating System :: Microsoft :: Windows
Classifier: Operating System :: POSIX :: Linux
Provides-Extra: cli
License-File: LICENSE
